LICENSE.txt
MANIFEST.in
README.md
README.txt
setup.cfg
setup.py
pbox/__init__.py
pbox/pbox.py
pbox.egg-info/PKG-INFO
pbox.egg-info/SOURCES.txt
pbox.egg-info/dependency_links.txt
pbox.egg-info/top_level.txt