Metadata-Version: 1.1
Name: pbox
Version: 2.6.0
Summary: Pbox is a simple module that makes it easier to handle persistent data using pickle or json.
Home-page: https://bitbucket.org/caveiramanca/pbox/
Author: Caveiramanca
Author-email: caveiramanca@gmail.com
License: LGPL
Download-URL: https://bitbucket.org/caveiramanca/pbox/src/master/dist/
Keywords: pickle,persistent data,cPickle,json
Platform: Posix
Platform: Windows
Classifier: Development Status :: 5 - Production/Stable
Classifier: Intended Audience :: Developers
Classifier: Operating System :: OS Independent
Classifier: Natural Language :: English
Classifier: Programming Language :: Python :: 2
Classifier: Programming Language :: Python :: 3
Classifier: Topic :: Software Development
Classifier: Topic :: Software Development :: Libraries :: pygame
Classifier: Topic :: Software Development :: Libraries :: Python Modules
Classifier: Topic :: Games/Entertainment
